agents/__init__.py
agents/adapters.py
agents/base.py
agents/orchestrator.py
agents/schemas.py
agents/tools.py
api/__init__.py
api/app.py
agentforgex-0.1.0.dist-info/METADATA
agentforgex-0.1.0.dist-info/WHEEL
agentforgex-0.1.0.dist-info/entry_points.txt
agentforgex-0.1.0.dist-info/top_level.txt
agentforgex-0.1.0.dist-info/RECORD
